data_enrichment_agent/__init__.py
data_enrichment_agent/agent.py
data_enrichment_agent/cli.py
data_enrichment_agent/config.py
data_enrichment_agent/constants.py
data_enrichment_agent/models.py
data_enrichment_agent/utils.py
data_enrichment_agent-0.1.1.dist-info/METADATA
data_enrichment_agent-0.1.1.dist-info/WHEEL
data_enrichment_agent-0.1.1.dist-info/entry_points.txt
data_enrichment_agent-0.1.1.dist-info/top_level.txt
data_enrichment_agent-0.1.1.dist-info/RECORD
